nau/__init__.py
nau/cli.py
nau/conf.ini
nau/config.py
nau/login.py
nau/loginHelper.py
nau/logout.py
nau/network.py
nau_net-1.0.2.dist-info/DESCRIPTION.rst
nau_net-1.0.2.dist-info/METADATA
nau_net-1.0.2.dist-info/RECORD
nau_net-1.0.2.dist-info/WHEEL
nau_net-1.0.2.dist-info/entry_points.txt
nau_net-1.0.2.dist-info/metadata.json
nau_net-1.0.2.dist-info/top_level.txt
nau_net-1.0.2.dist-info/zip-safe
