Metadata-Version: 2.0
Name: nau-net
Version: 1.0.2
Summary: NAU school network CLI.
Home-page: https://github.com/zhanba/nau_net
Author: zhanba
Author-email: c5e1856@gmail.com
License: MIT
Keywords: NAU network CLI
Platform: UNKNOWN
Classifier: Development Status :: 4 - Beta
Classifier: Intended Audience :: End Users/Desktop
Classifier: Topic :: Internet :: WWW/HTTP
Classifier: License :: OSI Approved :: MIT License
Classifier: Programming Language :: Python :: 2.7
Classifier: Programming Language :: Python :: 3.4
Classifier: Programming Language :: Python :: 3.5
Classifier: Programming Language :: Python :: 3.6
Requires-Dist: beautifulsoup4
Requires-Dist: click
Requires-Dist: future
Requires-Dist: requests
